yearmonth/__init__.py
yearmonth/_version.py
yearmonth/yearmonth.py
yearmonth-0.1.0.dist-info/LICENSE
yearmonth-0.1.0.dist-info/WHEEL
yearmonth-0.1.0.dist-info/METADATA
yearmonth-0.1.0.dist-info/RECORD
