Metadata-Version: 2.1
Name: yearmonth
Version: 0.1.0
Summary: A pydantic compatible yearmonth datatype
License: MIT
Author: bsnacks000
Author-email: bsnacks000@gmail.com
Requires-Python: >=3.7,<3.10
Classifier: License :: OSI Approved :: MIT License
Classifier: Programming Language :: Python :: 3
Classifier: Programming Language :: Python :: 3.7
Classifier: Programming Language :: Python :: 3.8
Classifier: Programming Language :: Python :: 3.9
